FreshServiceApi/__init__.py
FreshServiceApi-0.0.6.dist-info/LICENSE.txt
FreshServiceApi-0.0.6.dist-info/METADATA
FreshServiceApi-0.0.6.dist-info/WHEEL
FreshServiceApi-0.0.6.dist-info/top_level.txt
FreshServiceApi-0.0.6.dist-info/RECORD
