Metadata-Version: 2.1
Name: FreshServiceApi
Version: 0.0.6
Summary: Modules for the FreshService API
Home-page: UNKNOWN
Author: Stephen Fitzsimmons
License: MIT
Keywords: FreshService
Platform: UNKNOWN
Classifier: Development Status :: 4 - Beta
Classifier: Intended Audience :: Information Technology
Classifier: Operating System :: Microsoft :: Windows :: Windows 10
Classifier: License :: OSI Approved :: MIT License
Classifier: Programming Language :: Python :: 3
Requires-Dist: requests
